cmaketools/__init__.py
cmaketools/cmakebuilder.py
cmaketools/cmakecommands.py
cmaketools/cmakeutil.py
cmaketools/gitutil.py
cmaketools-0.1.6.dist-info/LICENSE
cmaketools-0.1.6.dist-info/METADATA
cmaketools-0.1.6.dist-info/WHEEL
cmaketools-0.1.6.dist-info/top_level.txt
cmaketools-0.1.6.dist-info/RECORD
