Metadata-Version: 2.1
Name: cmaketools
Version: 0.1.6
Summary: Seamless integration of Cmake build system to setuptools/distutils
Home-page: https://github.com/python-cmaketools/python-cmaketools
Author: Takeshi (Kesh) Ikuma
Author-email: tikuma@gmail.com
License: MIT License
Platform: UNKNOWN
Classifier: Development Status :: 3 - Alpha
Classifier: Intended Audience :: Developers
Classifier: Intended Audience :: End Users/Desktop
Classifier: License :: OSI Approved :: MIT License
Classifier: Programming Language :: Python :: 3
Classifier: Operating System :: OS Independent
Classifier: Topic :: Software Development :: Build Tools
Classifier: Topic :: Software Development :: Libraries :: Python Modules
Classifier: Topic :: System :: Archiving :: Packaging
Classifier: Topic :: Utilities
